Panache-0.2.12.dist-info/METADATA
Panache-0.2.12.dist-info/RECORD
Panache-0.2.12.dist-info/WHEEL
Panache-0.2.12.dist-info/entry_points.txt
Panache-0.2.12.dist-info/top_level.txt
panache/__init__.py
panache/panache.py
panache/version.py
