Metadata-Version: 2.1
Name: Panache
Version: 0.2.12
Summary: Pandoc wrapped in styles
Home-page: https://github.com/sebogh/panache
Author: Sebastian Bogan
Author-email: sebogh@qibli.net
License: BSD 3-Clause License
Platform: UNKNOWN
Classifier: Development Status :: 3 - Alpha
Classifier: License :: OSI Approved :: BSD License
Classifier: Programming Language :: Python :: 3.5
Classifier: Topic :: Text Processing :: Markup
Requires-Python: >3.5.0
Requires-Dist: pyyaml (>=4.2b1)
Requires-Dist: pystache
Requires-Dist: defusedxml
